annotate_variants_sl/__init__.py
annotate_variants_sl/ensembl.py
annotate_variants_sl/main.py
annotate_variants_sl-0.1.0.dist-info/LICENSE
annotate_variants_sl-0.1.0.dist-info/METADATA
annotate_variants_sl-0.1.0.dist-info/WHEEL
annotate_variants_sl-0.1.0.dist-info/entry_points.txt
annotate_variants_sl-0.1.0.dist-info/RECORD
