Metadata-Version: 2.1
Name: annotate_variants_sl
Version: 0.1.0
Summary: Command line tool to annotate files from Ensembl rest api.
License: MIT
Author: slebras
Requires-Python: >=3.9
Classifier: License :: OSI Approved :: MIT License
Classifier: Programming Language :: Python :: 3
Classifier: Programming Language :: Python :: 3.9
Classifier: Programming Language :: Python :: 3.10
Classifier: Programming Language :: Python :: 3.11
Classifier: Programming Language :: Python :: 3.12
Classifier: Programming Language :: Python :: 3.13
Requires-Dist: pandas (>=2.3.0,<3.0.0)
Requires-Dist: requests (>=2.32.4,<3.0.0)
Requires-Dist: responses (>=0.25.7,<0.26.0)
